energy_assistant_frontend/__init__.py
energy_assistant_frontend/apple-touch-icon.png
energy_assistant_frontend/energy-assistant.svg
energy_assistant_frontend/index.html
energy_assistant_frontend/manifest.webmanifest
energy_assistant_frontend/pwa-192x192.png
energy_assistant_frontend/pwa-512x512.png
energy_assistant_frontend/py.typed
energy_assistant_frontend/robots.txt
energy_assistant_frontend/sw.js
energy_assistant_frontend/workbox-e3490c72.js
energy_assistant_frontend/assets/CoreConfigs-BFQWQXLW.js
energy_assistant_frontend/assets/CoreConfigs-D_BQ-vpt.css
energy_assistant_frontend/assets/Default-B8IyWHeC.js
energy_assistant_frontend/assets/Default-BDThR6s7.css
energy_assistant_frontend/assets/Devices-D-aLGUNa.css
energy_assistant_frontend/assets/Devices-UqYRVXtw.js
energy_assistant_frontend/assets/EditDeviceConfig-Bz8adnuM.js
energy_assistant_frontend/assets/EditDeviceConfig-DYx9Yjpx.css
energy_assistant_frontend/assets/Forecast-DLsKOxTV.js
energy_assistant_frontend/assets/Forecast-DgrH56pG.js
energy_assistant_frontend/assets/Home-Dzpbk67-.js
energy_assistant_frontend/assets/JetBrainsMono-Medium-3S3k2nMz.woff2
energy_assistant_frontend/assets/MaterialIcons-Regular-BjXOXp5c.eot
energy_assistant_frontend/assets/MaterialIcons-Regular-DEUTIz1o.ttf
energy_assistant_frontend/assets/MaterialIcons-Regular-DOtZ65Va.woff2
energy_assistant_frontend/assets/MaterialIcons-Regular-FsbMSDLx.woff
energy_assistant_frontend/assets/PowerFlowCard-B6RsybhN.css
energy_assistant_frontend/assets/PowerFlowCard-D9lB7ADc.js
energy_assistant_frontend/assets/RawData-BVH8-qB0.js
energy_assistant_frontend/assets/RawData-BWipxmn5.css
energy_assistant_frontend/assets/SessionLog-C7pn5z0O.js
energy_assistant_frontend/assets/SessionLog-C_Pjwgt2.css
energy_assistant_frontend/assets/Settings-DCsSR0i8.js
energy_assistant_frontend/assets/Statistics-CASf-1LA.js
energy_assistant_frontend/assets/VBtn-CyybdnDU.js
energy_assistant_frontend/assets/VBtn-D9x-UhCY.css
energy_assistant_frontend-0.0.70.dist-info/METADATA
energy_assistant_frontend-0.0.70.dist-info/WHEEL
energy_assistant_frontend-0.0.70.dist-info/licenses/LICENSE
energy_assistant_frontend-0.0.70.dist-info/RECORD
