Metadata-Version: 2.4
Name: energy-assistant-frontend
Version: 0.0.70
Summary: The Energy Assistant frontend
Project-URL: Homepage, https://github.com/music-assistant/frontend
Author-email: The Energy Assistant Creators <pail23@users.noreply.github.com>
License: Apache-2.0
License-File: LICENSE
Requires-Python: >=3.12.0
